benchmark_model.py
chat_with_model.py
run_benchmark.py
visualize_benchmark.py
quantizer/__init__.py
quantizer/cli.py
quantizer/model_card.py
quantizer/model_quantizer.py
quantizer/quantization_config.py
model_quantizer-0.3.3.dist-info/LICENSE
model_quantizer-0.3.3.dist-info/METADATA
model_quantizer-0.3.3.dist-info/WHEEL
model_quantizer-0.3.3.dist-info/entry_points.txt
model_quantizer-0.3.3.dist-info/top_level.txt
model_quantizer-0.3.3.dist-info/RECORD
