Metadata-Version: 2.2
Name: model-quantizer
Version: 0.3.3
Summary: A tool for quantizing large language models
Home-page: https://github.com/lpalbou/model-quantizer
Author: Laurent-Philippe Albou
Author-email: laurent.albou@gmail.com
Classifier: Development Status :: 3 - Alpha
Classifier: Intended Audience :: Developers
Classifier: Intended Audience :: Science/Research
Classifier: License :: OSI Approved :: MIT License
Classifier: Programming Language :: Python :: 3
Classifier: Programming Language :: Python :: 3.8
Classifier: Programming Language :: Python :: 3.9
Classifier: Programming Language :: Python :: 3.10
Classifier: Programming Language :: Python :: 3.11
Classifier: Programming Language :: Python :: 3.12
Classifier: Topic :: Scientific/Engineering :: Artificial Intelligence
Requires-Python: >=3.8
License-File: LICENSE
Requires-Dist: transformers>=4.30.0
Requires-Dist: huggingface_hub>=0.16.0
Requires-Dist: numpy==1.26.4
Requires-Dist: psutil==7.0.0
Requires-Dist: tqdm==4.67.1
Provides-Extra: dev
Requires-Dist: pytest==7.4.0; extra == "dev"
Requires-Dist: black==25.1.0; extra == "dev"
Requires-Dist: isort==6.0.0; extra == "dev"
Requires-Dist: flake8>=6.0.0; extra == "dev"
Provides-Extra: viz
Requires-Dist: matplotlib==3.10.0; extra == "viz"
Requires-Dist: colorama>=0.4.6; extra == "viz"
Requires-Dist: jinja2==3.1.5; extra == "viz"
Provides-Extra: data
Requires-Dist: datasets==3.4.0; extra == "data"
Requires-Dist: accelerate==1.5.2; extra == "data"
Provides-Extra: gptq
Requires-Dist: optimum[gptq]==1.24.0; extra == "gptq"
Requires-Dist: gptqmodel<2.1.0; extra == "gptq"
Provides-Extra: bitsandbytes
Requires-Dist: bitsandbytes==0.42.0; extra == "bitsandbytes"
Provides-Extra: awq
Requires-Dist: autoawq>=0.1.0; extra == "awq"
Provides-Extra: all
Requires-Dist: pytest==7.4.0; extra == "all"
Requires-Dist: black==25.1.0; extra == "all"
Requires-Dist: isort==6.0.0; extra == "all"
Requires-Dist: flake8>=6.0.0; extra == "all"
Requires-Dist: matplotlib==3.10.0; extra == "all"
Requires-Dist: colorama>=0.4.6; extra == "all"
Requires-Dist: jinja2==3.1.5; extra == "all"
Requires-Dist: datasets==3.4.0; extra == "all"
Requires-Dist: accelerate==1.5.2; extra == "all"
Requires-Dist: optimum[gptq]==1.24.0; extra == "all"
Requires-Dist: gptqmodel<2.1.0; extra == "all"
Requires-Dist: bitsandbytes==0.42.0; extra == "all"
Requires-Dist: autoawq>=0.1.0; extra == "all"
Dynamic: author
Dynamic: author-email
Dynamic: classifier
Dynamic: description
Dynamic: description-content-type
Dynamic: home-page
Dynamic: provides-extra
Dynamic: requires-dist
Dynamic: requires-python
Dynamic: summary
